<?xml version="1.0" encoding="UTF-8" standalone="yes"?>
<contentHaul xmlns:a="http://www.appian.com/ae/types/2009">
    <queryRule>
        <name>AC_GetAllUserDetailByUserName</name>
        <uuid>_a-0000db81-7a28-8000-5130-010000010000_2874</uuid>
        <description>Returns all user detail by user name</description>
        <folderUuid>_a-0000db81-7a28-8000-5130-010000010000_2572</folderUuid>
        <dataStoreEntityCompositeUuid>7170b2a3-d01e-4815-b1b1-8e19f0177ca1@_a-0000db81-7a28-8000-5130-010000010000_2392</dataStoreEntityCompositeUuid>
        <params>
            <param>
                <description></description>
                <name>UserName</name>
                <type>{http://www.w3.org/2001/XMLSchema}string</type>
            </param>
        </params>
        <filters>
            <filter>
                <field>
                    <name>Username</name>
                    <type>{http://www.w3.org/2001/XMLSchema}string</type>
                </field>
                <op>=</op>
                <value>UserName</value>
                <valueType>PARAMETER</valueType>
            </filter>
        </filters>
        <orderings/>
    </queryRule>
    <roleMap public="false">
        <role allowForAll="false" inherit="true" name="readers">
            <users/>
            <groups/>
        </role>
        <role allowForAll="false" inherit="true" name="authors">
            <users/>
            <groups/>
        </role>
        <role allowForAll="false" inherit="true" name="administrators">
            <users>
                <userUuid>kshama.gupta</userUuid>
            </users>
            <groups/>
        </role>
        <role allowForAll="false" inherit="false" name="denyReaders">
            <users/>
            <groups/>
        </role>
        <role allowForAll="false" inherit="false" name="denyAuthors">
            <users/>
            <groups/>
        </role>
        <role allowForAll="false" inherit="false" name="denyAdministrators">
            <users/>
            <groups/>
        </role>
    </roleMap>
</contentHaul>
